README.md
setup.py
HistWithAdditives2/Prettyhist.py
HistWithAdditives2/__init__.py
HistWithAdditives2.egg-info/PKG-INFO
HistWithAdditives2.egg-info/SOURCES.txt
HistWithAdditives2.egg-info/dependency_links.txt
HistWithAdditives2.egg-info/top_level.txt