Metadata-Version: 1.2
Name: HistWithAdditives2
Version: 0.0.1
Summary: Making a labelled histogram
Home-page: UNKNOWN
Author: John Njeri
Author-email: waiganjojohn11@gmail.com
License: UNKNOWN
Platform: UNKNOWN
Classifier: Programming Language :: Python :: 3
Classifier: License :: OSI Approved :: MIT License
Classifier: Operating System :: OS Independent
Requires-Python: >=3.6
